{"pM03dabhDqXUaiEdtnjjbA==":"chloe-bolton-r0qthxq3jec-unsplash99.jpeg","fazqRvUTnsGgtdkXAKxbpg==":"chloe-bolton-r0qthxq3jec-unsplash99.jpg","ZA/gNSBMsPLGzD9oofWtGg==":"chloe-bolton-l-bxrw-bz9i-unsplash.jpeg","+8YX7kNJcx4/ZEBWB28Txw==":"clayton-robbins-e3b0j05ic20-unsplash-1.jpg","NMINYDU06dL9gnx+zEFATg==":"clayton-robbins-ypynhyr7xrs-unsplash-1.jpg","SYO4I2gJ/3kV2ayFEfLCRA==":"clayton-robbins-kmzrutvsqai-unsplash-1.jpg","QkhU6GJCJl7GmxgiWuiMWw==":"grant-durr-vfgskggimaa-unsplash-1.jpg","IfNPsHqfO2nKGvAI/A3zcg==":"fernando-lavin-qxaavqecvew-unsplash-1.jpg","cLJadrIaogcdr4JkjzjI9g==":"faria-anzum-onk9ilkizs4-unsplash.jpg","cha0b7cQ8LVoexeP9Vndqg==":"annie-spratt-n42ogaqn32o-unsplash.jpg","GXzPB+NLWU8H2EdogtG93g==":"amin-hasani-kiifsibhkqw-unsplash.jpg","S2t9hq8nEPTXfgTt7Smavg==":"christy-moyer-5ippjvbbyo-unsplash.jpg","XqStexa3ucYeWEdbgE9USg==":"background1.jpg","gcg7mOw5bgl+bDj01ICzXA==":"shot-72.png","NjagmuN00dD4iqPgpmm6tQ==":"screenshot-73.jpg","lD9RWIg1EXLBi/Z5IdbPHw==":"screenshot-116.jpg","t0I3UvbPnQSlp3kFlU0DPg==":"chloe-bolton-r0qthxq3jec-unsplash99.jpeg","8tKKKhKV1924yqh/Z2UrOQ==":"banner-1600x900.jpg","Z+/BGmPU5U44OHWvyqA5uw==":"whatsapp%20image%202024-06-08%20at%203.58.24%20pm-96x95.jpg","m8Goc/Ak2ZYz+9hnFlzu0A==":"whatsapp%20image%202024-06-08%20at%203.58.24%20pm-97x96.jpg","EFC9tjlX9EC+T/1WpBuXnQ==":"whatsapp%20image%202024-06-08%20at%203.58.24%20pm-97x96.jpg","j7vnbQUgvRXaEGWEnNM4Fg==":"photo1717835222-removebg-preview-97x86.png","7EF/Zhsiz/1ZnrCPCDEIow==":"photo1718115685-851x315.jpg","kaPFRYf3xqglmpsgkd38IA==":"3-851x315.png","D4fijv9m6e9y7Atxt4c+RA==":"1-851x315.png","l0KupqMFNyJE/BPplnstxQ==":"4-851x315.png","0AHLwJVUd3ttxbdZjyoR0Q==":"6-851x315.png","Jn7MVQ8Tj6EWP5g+SMfmTw==":"2-851x315.png","qLmgIPiBunXpiKeOU9b1rg==":"7-851x315.png","5vVCd1StFx/Bzne8A6yPxg==":"8-851x315.png","CkGVqziN/J3EDBXZ8Mox1w==":"9-851x315.png","HfUC3ij1HujyeZsl4/GSPw==":"10-851x315.png","6/DeEr3bor4tsGXT/g8WlA==":"banner%20(3)-851x315.png","yDQF7kBvuXbZ1xw2+3Fyvg==":"whatsapp%20image%202024-06-08%20at%203.58.24%20pm-400x397.jpg","X6VayT+2NdybmQVKPfg/BQ==":"malaysia-2000x1000.png","RoSxF6UfKdW4N95Ke09i3w==":"malaysia-1695x848.png","rEpeL0ZiZEKH0sXx3YMZLw==":"untitled%20design%20(3)-815x458.png","TYwM70y3sjsNHKVUPH+nEQ==":"retouch-2024060900440967-815x611.jpeg","4WKolZLZOTzNx8ogKl/dvQ==":"monochrome_minimalist_elegant_magazine_photography_portfolio_presentation-815x611.png","0CVvyNlWQP7R8Lv+ih5x8w==":"monochrome_minimalist_elegant_magazine_photography_portfolio_presentation%20(1)-815x611.png","OnRYSYtb0+hVUE/hkI0tCQ==":"untitled%20design%20(3)-1920x1080.png","L60xHbVVCxY2eMZHwfReGg==":"3-815x611.png","4AKOIGDLgLKK74OUGG+a1A==":"4-815x611.png","5LsRCmPvYpej80dcQU8RZw==":"malaysia-1980x990.png","hQHO17oWGFNp/x/9h9/zOg==":"offer-1442x798.jpg","KTcqjC8y55aVHPEbnv5hog==":"offer2-1800x1002.jpg","TnnDzB0/rRH1aX9DtS6mHg==":"offer3-1980x1097.jpg","URJk2Pn2GWbDwB+N8IIUNA==":"offer2-1980x1102.jpg","hK3mGe0MlRaGpSESEeOM0w==":"banner%20(6)-851x315.png","OvTcgl3kD5aZe7HkVSHWBQ==":"photo1718543673-815x367.jpg","NDsNXnrSXPQ9zdPWgV2rxg==":"11-815x815.png","Dx2aEX1RLEQJk8ysL0nwbA==":"11-1-815x815.png","MLPtxS4+msFFRIArn5YoNA==":"88-815x815.png","3OG0Ae0SfJkhsiD0C3Ln3w==":"88-1-815x815.png","GtrUtpPIiIWwjnuB/O/cqQ==":"88-2-815x815.png","2VSe2I4w8it6SFRtfYJgTg==":"photo1718544209-815x367.jpg","63ibxidGxuK4XBB5XfdCuw==":"photo1718544209-815x367.jpeg","+IlM8GBrD24jkqI0xatsqQ==":"photo1718544209-1-815x367.jpeg","Lar3Rt9yfq+E8wh7D7HJLA==":"photo1718544209%20(1)-815x367.jpeg","U4KvJj4fY4sxcK5NBX8CtQ==":"photo1718544209%20(2)-2560x1152.jpg","J2XumQIO8TuzKp6a5FnIUQ==":"photo1718544209%20(2)-2560x1152.jpeg","OMKIW6JYjngjRH8vEq/juw==":"mc-815x815.png","lVJyoxlfDJAMyHcI0mw1UQ==":"mc-1-815x815.png","SPHK/3FKAfkTEIGIggDnnQ==":"mc2-815x815.png","527CF2v1SwsqiKYXXTqb2w==":"mc3-815x815.png","6eYdO/3s2bYpKjH5ncWftQ==":"mc4-1080x1080.png","wZeRJ2iKqggsJFQh7eUJVQ==":"mc5-1080x1080.png","qH/Pyno613B9PvuM5DqOPw==":"mc6-1080x1080.png","Mip45X2UQE1Wum9wBtZiHg==":"mc7-1080x1080.png","2Yo3w8nLrEaju1y0QQKEfg==":"mc5-1-1080x1080.png","Tqi5zk3USFMcxZxG0da1Kg==":"mc5-815x815.png","CutkiOlGD5mWkjvtUSfJLA==":"mr1-815x815.png","BinPQMbDLU2DsyxXHTuqTw==":"mr2-815x815.png","GDA0fiZT+GTN3i98JK7HPQ==":"mr3-1080x1080.png","ztxmeypyc+gDnJblYi5y4Q==":"mr3-1-1080x1080.png","8yw0Z/o4lVo7XB96hQtcGg==":"pudding%20(2)-815x367.jpg","2h/LXk7JYltxDv8j1IpUKA==":"pudding-815x367.jpg","OYnLguOQaqJ9MHbAGn5V/w==":"pudding2-815x367.jpg","LS4To9u6RV+gvgPiryib1w==":"pudding3-4000x1800.jpg","h72otRrxnSLR2c1SjK8+rw==":"pudding4-4000x1800.jpg","uqF9e8/6acupQWBq6qwOIg==":"pudding5-4000x1800.jpg","raSyaL0cVVU7hNhyvdpIUA==":"myself5-145x194.jpg","n5oRZM89PgHiM7sKk+PHHA==":"myself5-145x194.jpeg","UHwOHia1VDywkSg5OWxpWA==":"15-815x815.png","Hdv7zujkS6XZJYU8N1QigQ==":"16-815x815.png","IhoW3hLyH7HoZEAXX5YoJQ==":"16-1-815x815.png","+HzLcbBbMlTqYWHLlBWJGA==":"17-815x815.png","TeoBAczP7zmMcXh6m3TVrg==":"17-1-815x815.png","hTYTg3XqWtdjyHKbTJZH6A==":"18-1080x1080.png","dM4atogQsU8n68XukNgVog==":"19-1080x1080.png","6sAQezH3xsy8RgSrthbi+w==":"drink7-1080x2400.jpg","m+daBXwnF/pJmLmgzGTzaA==":"drink7-1800x4000.jpg","L+ZwOGaKcvKVpXSP7UgU5Q==":"16-2-815x815.png","uGcmXpIKt2PlA6JBPtTXJQ==":"16-3-815x815.png","a72KfWJZOYLtFD7WEOUl9A==":"16-4-815x815.png","KMOMTc1qM2mSEcMEP/5Z5w==":"16-5-815x815.png","M9nN2NEHzTh8ufXyHFSCuw==":"17-2-815x815.png","IbGIdGxh8zFRDNfoytjmIg==":"17-3-815x815.png","tGSyYvc4zq5A08PwWTVZXw==":"17-4-815x815.png","lgZr1grsMdqQJM59Hh14/g==":"17-5-815x815.png","Ivm27DF1IWVjoIDu4FgTwQ==":"15-1-815x815.png","q9c86BRg07qqS4P2J8H9aA==":"banner%20(3)-851x315.png","z7i9L9MbzFXtAkpdKpJaSQ==":"6-1-851x315.png","kxf2dFTT6gygG24LyESlWA==":"7-1-851x315.png","LA+VPYTdXqfZ3diKbCg3kA==":"8-1-851x315.png","b7RQgHCi+LP8B0VXpuN2Ug==":"9-1-851x315.png","4sBq93qFVCR/BxQ0Z+SgHg==":"10-1-851x315.png","h+DudBBTRCgak22CVkWHzA==":"mc5-1-815x815.png","loIe8T9rY254BQITIlVa6A==":"mc5-2-815x815.png","rdwMXLDctlBP6o3p/01wsw==":"mc2-1-815x815.png","pO8NepYZ7rnoOgcTiw/+7w==":"pudding2-815x367.jpeg","6kbjHsc5mxLBrQtJU81KmQ==":"screenshot%202024-06-23%20191307-1256x597.png","2slvDdH4mrTPYkrW83/ucA==":"screenshot%202024-06-23%20191307-1256x597.png","/8Tk995tCVYTrJVaqXpwtg==":"screenshot%202024-06-23%20191420-1256x574.png","Rf68tdvRPSqzh3yQeB2edA==":"screenshot%202024-06-23%20191420-1256x574.png","kpu4q2ctYD+bH3/U2Rdmaw==":"drink9%20(1)-270x405.jpg","uqKea5B6qMdBFytvn0FA+A==":"drink9%20(1)-270x405.jpeg","9J6jR3D+RYZUTAlalpGi1w==":"photo1719143281-815x1087.jpg","t52pZQbE+KL6c+n8oVmTwQ==":"photo1719143289-815x1083.jpg","VTZOQ+jmItAcmlG3aVhKhg==":"20-1080x1080.png","zVWWVeieB4mnY6LACRpCRw==":"20-1-1080x1080.png","uer9/Ng7omN1FHeMjcP1vA==":"20-2-1080x1080.png","nVM82l6t5dul/LUi5RIBew==":"20-815x815.png","H7JsbYiympFeEDFGnUlSAg==":"20-1-815x815.png","rxO7MBT+ZMZJE4IFsKFXzQ==":"20-2-815x815.png","pErCtcJT9q3dkhlxeq3ZVA==":"20-3-815x815.png","Env3LnEnevv8OKAQwJqPkA==":"20-4-815x815.png","YIX24kMJjA3zBzJE7YOpJQ==":"20-5-815x815.png","6uN94ES/CgJ6+Hok45FTlw==":"banner%20(6)-851x315.png","Fjy7KN0560qtAVWPNT269Q==":"offer-739x409.jpg","DzoQNW0KKb5XIU5NTW6zuA==":"offer3-1800x998.jpg","PGeScAwG5VhMsN9jx+p9NA==":"malaysia.gif","VegSlo1gmVCvYg+y4ZoCuQ==":"myself6-810x1080.jpeg","FmiygDtnflWZjOesfGjLog==":"photo1719143289-815x1083.jpeg","CrqWfLiekQoCodxftGUJww==":"photo1719143289-1-815x1083.jpeg","uMo0slaHm7XBWbcz9wu//A==":"whatsapp%20image%202024-06-24%20at%2012.31.06%20pm-815x1344.jpg","KMA6gwPNEmjFt0N2cOv2qg==":"whatsapp%20image%202024-06-24%20at%2012.31.06%20pm-815x1344.jpeg","VySYnJfgMZ8QHsudBxNX5Q==":"malaysia%20(1).gif","6kKzFRloNDNJw60JGscbWA==":"malaysia%20(2).gif","hP8kNBcRObNx+rXnunqQQw==":"offerbanner1.gif","pzIXyKMIxqdR0jaVvcxW2w==":"offerbanner2.gif","dsKd/6kd9WNmXs1cNRgjHg==":"20-3-1080x1080.png","fCdzkeAYUoUesdeTBk8SFQ==":"21-1080x1080.png","hS3WDGLcle6fxty6xWTE6Q==":"22-1080x1080.png","gM4k/g7yjVcCeOzxl9+/gA==":"23-1080x1080.png","fcR4eQ+TF9kdUvcn6djGRg==":"offerbanner2%20(1).gif","k/RybxPktElGCrSvlzPg2g==":"offerbanner1%20(1).gif","HBSHmlSS9Gn70lnd5c0+cQ==":"offerbanner2%20(1).png"}